continual/__init__.py
continual/python/__init__.py
continual/python/blob/__init__.py
continual/python/blob/gcs.py
continual/python/blob/gcs_test.py
continual/python/blob/store.py
continual/python/cli/__init__.py
continual/python/cli/batch_predictions.py
continual/python/cli/changes.py
continual/python/cli/cli.py
continual/python/cli/config.py
continual/python/cli/devtools.py
continual/python/cli/environments.py
continual/python/cli/events.py
continual/python/cli/experiments.py
continual/python/cli/extensions.py
continual/python/cli/feature_sets.py
continual/python/cli/featurestore_config.py
continual/python/cli/ingestions.py
continual/python/cli/model_versions.py
continual/python/cli/models.py
continual/python/cli/organizations.py
continual/python/cli/projects.py
continual/python/cli/promotions.py
continual/python/cli/reports.py
continual/python/cli/tests/test_utils.py
continual/python/cli/tests/test_utils_dbt.py
continual/python/cli/users.py
continual/python/cli/utils.py
continual/python/cli/utils_dbt.py
continual/python/examples/bank_marketing/bank_marketing.yaml
continual/python/examples/bank_marketing/bank_marketing_train.csv
continual/python/examples/kickstarter/kickstarter.yaml
continual/python/examples/kickstarter/kickstarter_train.csv
continual/python/extras/featureset_reference_schema.yaml
continual/python/extras/model_reference_schema.yaml
continual/python/sdk/__init__.py
continual/python/sdk/batchpredictions.py
continual/python/sdk/changes.py
continual/python/sdk/client.py
continual/python/sdk/config.py
continual/python/sdk/datasets.py
continual/python/sdk/environments.py
continual/python/sdk/events.py
continual/python/sdk/exceptions.py
continual/python/sdk/experiments.py
continual/python/sdk/extensions/__init__.py
continual/python/sdk/extensions/algorithms/__init__.py
continual/python/sdk/extensions/algorithms/base_custom_algorithm.py
continual/python/sdk/extensions/models/__init__.py
continual/python/sdk/extensions/models/base_model_pipeline.py
continual-0.5.87.dist-info/entry_points.txt
continual-0.5.87.dist-info/WHEEL
continual-0.5.87.dist-info/METADATA
continual-0.5.87.dist-info/RECORD
