Metadata-Version: 2.1
Name: continual
Version: 0.5.87
Summary: Operational AI for the Modern Data Stack
Author: Continual
Author-email: support@continual.ai
Requires-Python: >=3.8,<3.11
Classifier: Programming Language :: Python :: 3
Classifier: Programming Language :: Python :: 3.10
Classifier: Programming Language :: Python :: 3.8
Classifier: Programming Language :: Python :: 3.9
Requires-Dist: GitPython (>=3.1.27)
Requires-Dist: click (==8.0.4)
Requires-Dist: cloudpickle (>=2.0.0)
Requires-Dist: cron-descriptor (>=1.2.24)
Requires-Dist: databricks_api (>=0.8.0)
Requires-Dist: dill (>=0.3.4)
Requires-Dist: fsspec (==2022.3)
Requires-Dist: gitpython (>=3.1.7)
Requires-Dist: google-cloud-storage (>=1.33.0)
Requires-Dist: grpcio (>=1.27.1)
Requires-Dist: grpcio-tools (>=1.43.0,<=1.48.1)
Requires-Dist: grpcio_status (>=1.31.0)
Requires-Dist: halo (>=0.0.30)
Requires-Dist: humanize (>=2.5.0)
Requires-Dist: jinja2 (>=3.1.1)
Requires-Dist: mlflow (>=1.23.1)
Requires-Dist: numpy (>=1.21.6)
Requires-Dist: pandas (>=1.0.1)
Requires-Dist: pandas-gbq (>=0.14.1)
Requires-Dist: poetry (>=0.12)
Requires-Dist: protobuf (==3.20.3)
Requires-Dist: psutil (>=5.8.0)
Requires-Dist: pyhive (>=0.6.4)
Requires-Dist: pytz (>=2020.5)
Requires-Dist: pyyaml (>=5.4)
Requires-Dist: requests (>=2.23.0)
Requires-Dist: rich (>=9.13.0)
Requires-Dist: scikit_learn (>=1.1.2)
Requires-Dist: shortuuid (>=1.0.9)
Requires-Dist: simplejson (>=3.17.6)
Requires-Dist: snowflake-sqlalchemy (>=1.3.3)
Requires-Dist: sqlalchemy (>=1.4.27)
Requires-Dist: sqlalchemy-bigquery (>=1.4.3)
Requires-Dist: sqlalchemy-redshift (>=0.8.9)
Requires-Dist: sqlparse (>=0.4.2)
Requires-Dist: tableschema (>=1.20.2)
Requires-Dist: tabulate (>=0.8.6)
Requires-Dist: toml (>=0.10.2)
Requires-Dist: tqdm (>=4.54.1)
Requires-Dist: typer (==0.4.0)
Requires-Dist: yamale (>=4.0.0)
